setup.py
mongodb_cache/__init__.py
mongodb_cache/cache.py
mongodb_cache/mongodb.py
mongodb_cache.egg-info/PKG-INFO
mongodb_cache.egg-info/SOURCES.txt
mongodb_cache.egg-info/dependency_links.txt
mongodb_cache.egg-info/top_level.txt