Metadata-Version: 1.0
Name: mongodb-cache
Version: 1.3
Summary: Useful to have consistent and simple cache in multi-datacenter installations. See github README.
Home-page: git@github.com:antonyc/mongodb_cache.git
Author: Anton Chaporgin
Author-email: chapson@yandex-team.ru
License: UNKNOWN
Platform: UNKNOWN
